discord/ext/typed_commands/__init__.py
discord/ext/typed_commands/__init__.pyi
discord/ext/typed_commands/py.typed
discord_ext_typed_commands-1.0.3.dist-info/LICENSE
discord_ext_typed_commands-1.0.3.dist-info/WHEEL
discord_ext_typed_commands-1.0.3.dist-info/METADATA
discord_ext_typed_commands-1.0.3.dist-info/RECORD
