Metadata-Version: 2.1
Name: discord-ext-typed-commands
Version: 1.0.3
Summary: Typed commands for discord.py
Home-page: https://github.com/bryanforbes/discord-ext-typed-commands
License: BSD-3-Clause
Author: Bryan Forbes
Author-email: bryan@reigndropsfall.net
Requires-Python: >=3.6.1,<4.0.0
Classifier: Development Status :: 4 - Beta
Classifier: Intended Audience :: Developers
Classifier: License :: OSI Approved :: BSD License
Classifier: Programming Language :: Python :: 3
Classifier: Programming Language :: Python :: 3.7
Classifier: Programming Language :: Python :: 3.8
Classifier: Programming Language :: Python :: 3.9
Classifier: Typing :: Typed
Requires-Dist: discord.py (>=1.4.1,<2.0.0)
Requires-Dist: importlib_metadata (>=1.7,<4.0); python_version < "3.8"
Requires-Dist: typing-extensions (>=3.7.4,<4.0.0); python_version < "3.8"
